cwl2click/__about__.py
cwl2click/__init__.py
cwl2click/cli.py
cwl2click/templates/command_line_tools.py
cwl2click-0.6.0.dist-info/METADATA
cwl2click-0.6.0.dist-info/WHEEL
cwl2click-0.6.0.dist-info/entry_points.txt
cwl2click-0.6.0.dist-info/licenses/LICENSE
cwl2click-0.6.0.dist-info/licenses/NOTICE
cwl2click-0.6.0.dist-info/RECORD
